fapi/__init__.py
fapi/foxford_api.py
fapi/foxford_api_classes.py
fapi/foxford_api_datatypes.py
fapi/foxford_api_errors.py
FOXFORD_API-0.1.2.dist-info/LICENSE
FOXFORD_API-0.1.2.dist-info/METADATA
FOXFORD_API-0.1.2.dist-info/WHEEL
FOXFORD_API-0.1.2.dist-info/top_level.txt
FOXFORD_API-0.1.2.dist-info/RECORD
