Metadata-Version: 2.1
Name: FOXFORD_API
Version: 0.1.2
Summary: FOXFORD Student API
Author: VOLT_DIAMOND
License: MIT License
Classifier: Programming Language :: Python :: 3
Classifier: License :: OSI Approved :: MIT License
Classifier: Operating System :: OS Independent
License-File: LICENSE
Requires-Dist: undetected-chromedriver
Requires-Dist: selenium
Requires-Dist: requests
Requires-Dist: aiohttp
